setup.cfg
setup.py
cred/__init__.py
cred/client.py
cred_client.egg-info/PKG-INFO
cred_client.egg-info/SOURCES.txt
cred_client.egg-info/dependency_links.txt
cred_client.egg-info/top_level.txt