Metadata-Version: 1.1
Name: cred-client
Version: 0.2.6
Summary: Client Library for cred-server.
Home-page: https://github.com/Tehnix/cred-client
Author: Tehnix
Author-email: ckl@codetalk.io
License: BSD
Download-URL: https://github.com/Tehnix/cred-client/tarball/v0.2.6
Platform: UNKNOWN
Classifier: Development Status :: 3 - Alpha
Classifier: Environment :: Console
Classifier: Intended Audience :: Developers
Classifier: Intended Audience :: System Administrators
Classifier: License :: OSI Approved :: BSD License
Classifier: Operating System :: MacOS :: MacOS X
Classifier: Operating System :: POSIX
Classifier: Programming Language :: Python :: 3 :: Only
Classifier: Topic :: Home Automation
